{"zingmp3.vn":{"/":{"zmp3_app_version.1":{"key":"zmp3_app_version.1","value":"119","expires":"2022-04-29T12:09:57.000Z","maxAge":31536000,"domain":"zingmp3.vn","path":"/","hostOnly":false,"creation":"2021-04-29T12:09:57.472Z","lastAccessed":"2021-05-11T08:39:22.026Z"},"zmp3_rqid":{"key":"zmp3_rqid","value":"MHwxNC4xNjkdUngMjM3LjI1NXwxMTl8MTYyMDmUsICyMjM2MjY4MQ","expires":"2021-07-15T08:39:22.000Z","maxAge":5616000,"domain":"zingmp3.vn","path":"/","hostOnly":false,"creation":"2021-04-29T12:09:57.479Z","lastAccessed":"2021-05-11T08:39:22.245Z"}}}}